LICENSE
README.md
setup.py
list_reserve/__init__.pyi
list_reserve/py.typed
list_reserve.egg-info/PKG-INFO
list_reserve.egg-info/SOURCES.txt
list_reserve.egg-info/dependency_links.txt
list_reserve.egg-info/top_level.txt
src/list_reserve.c