Metadata-Version: 2.1
Name: list-reserve
Version: 0.3.1
Summary: Python builtin list memory allocation library
Home-page: https://github.com/ChanTsune/list-reserve
Author: ChanTsune
Author-email: yshegou@gmail.com
License: MIT
Keywords: list extension memory reserve capacity
Platform: UNKNOWN
Classifier: Programming Language :: Python
Classifier: Programming Language :: Python :: 3
Classifier: Programming Language :: Python :: 3.5
Classifier: Programming Language :: Python :: 3.6
Classifier: Programming Language :: Python :: 3.7
Classifier: Programming Language :: Python :: 3.8
Classifier: Programming Language :: Python :: 3.9
Classifier: Programming Language :: Python :: 3.10
Classifier: License :: OSI Approved :: MIT License
License-File: LICENSE
